{"nodes":[{"id":"src_controllers_projectcontroller_js","label":"projectController","source_file":".\\src\\controllers\\projectController.js","node_type":"file"},{"id":"src_controllers_projectcontroller_js_listprojects","label":"listProjects()","source_file":".\\src\\controllers\\projectController.js","source_location":"L9","node_type":"function"},{"id":"src_controllers_projectcontroller_js_createproject","label":"createProject()","source_file":".\\src\\controllers\\projectController.js","source_location":"L26","node_type":"function"},{"id":"src_controllers_projectcontroller_js_deleteproject","label":"deleteProject()","source_file":".\\src\\controllers\\projectController.js","source_location":"L47","node_type":"function"}],"edges":[{"source":"src_controllers_projectcontroller_js","target":"src_controllers_projectcontroller_js_listprojects","relation":"defines","confidence":"EXTRACTED","confidence_score":1.0,"source_file":".\\src\\controllers\\projectController.js","source_location":"L9","weight":1.0},{"source":"src_controllers_projectcontroller_js","target":"src_controllers_projectcontroller_js_createproject","relation":"defines","confidence":"EXTRACTED","confidence_score":1.0,"source_file":".\\src\\controllers\\projectController.js","source_location":"L26","weight":1.0},{"source":"src_controllers_projectcontroller_js","target":"src_controllers_projectcontroller_js_deleteproject","relation":"defines","confidence":"EXTRACTED","confidence_score":1.0,"source_file":".\\src\\controllers\\projectController.js","source_location":"L47","weight":1.0}],"hyperedges":[]}